tools/LIBzek.py
tools/LIBzx.py
tools/__init__.py
CFelTools-0.0.6.dist-info/METADATA
CFelTools-0.0.6.dist-info/WHEEL
CFelTools-0.0.6.dist-info/top_level.txt
CFelTools-0.0.6.dist-info/RECORD
