Metadata-Version: 2.1
Name: CFelTools
Version: 0.0.6
Summary: cftools
Home-page: https://cubefel.netlify.app
Author: feleg
Author-email: false.fas527@gmail.com
Keywords: cfPass
Requires-Python: >=3.10
Requires-Dist: requests.txt
